PyScratchAuth/__init__.py
PyScratchAuth/auth.py
pyscratchauth-1.0.0b0.dist-info/METADATA
pyscratchauth-1.0.0b0.dist-info/WHEEL
pyscratchauth-1.0.0b0.dist-info/top_level.txt
pyscratchauth-1.0.0b0.dist-info/RECORD
